{
    "home-manager": {
        "branch": "master",
        "description": "Manage a user environment using Nix  [maintainer=@rycee] ",
        "homepage": "https://nix-community.github.io/home-manager/",
        "owner": "rycee",
        "repo": "home-manager",
        "rev": "6ce3493a3c5c6a8f4cfa6f5f88723272e0cfd335",
        "sha256": "09mrmrbvi2f3wd6dwyqqkc2lsyb8ljqwv84f1z6lffiyjdvz6vm7",
        "type": "tarball",
        "url": "https://github.com/rycee/home-manager/archive/6ce3493a3c5c6a8f4cfa6f5f88723272e0cfd335.tar.gz",
        "url_template": "https://github.com/<owner>/<repo>/archive/<rev>.tar.gz"
    },
    "niv": {
        "branch": "master",
        "description": "Easy dependency management for Nix projects",
        "homepage": "https://github.com/nmattia/niv",
        "owner": "nmattia",
        "repo": "niv",
        "rev": "351d8bc316bf901a81885bab5f52687ec8ccab6e",
        "sha256": "1yzhz7ihkh6p2sxhp3amqfbmm2yqzaadqqii1xijymvl8alw5rrr",
        "type": "tarball",
        "url": "https://github.com/nmattia/niv/archive/351d8bc316bf901a81885bab5f52687ec8ccab6e.tar.gz",
        "url_template": "https://github.com/<owner>/<repo>/archive/<rev>.tar.gz"
    },
    "nixpkgs": {
        "branch": "nixos-unstable",
        "description": "Nix Packages collection",
        "homepage": "",
        "owner": "NixOS",
        "repo": "nixpkgs",
        "rev": "093268502280540a7f5bf1e2a6330a598ba3b7d0",
        "sha256": "04bb9ng97y9anrc1khd99lsr7pf55x7scij8c5v2dzrikaxshi12",
        "type": "tarball",
        "url": "https://github.com/NixOS/nixpkgs/archive/093268502280540a7f5bf1e2a6330a598ba3b7d0.tar.gz",
        "url_template": "https://github.com/<owner>/<repo>/archive/<rev>.tar.gz"
    }
}
