{
    "home-manager": {
        "branch": "master",
        "description": "Manage a user environment using Nix  [maintainer=@rycee] ",
        "homepage": "https://nix-community.github.io/home-manager/",
        "owner": "rycee",
        "repo": "home-manager",
        "rev": "64831f938bd413cefde0b0cf871febc494afaa4f",
        "sha256": "0agzxdfl7x2grwbw5j71w3pw2dfjxgy499nf2bg01r4yyqsvgabi",
        "type": "tarball",
        "url": "https://github.com/rycee/home-manager/archive/64831f938bd413cefde0b0cf871febc494afaa4f.tar.gz",
        "url_template": "https://github.com/<owner>/<repo>/archive/<rev>.tar.gz"
    },
    "niv": {
        "branch": "master",
        "description": "Easy dependency management for Nix projects",
        "homepage": "https://github.com/nmattia/niv",
        "owner": "nmattia",
        "repo": "niv",
        "rev": "82e5cd1ad3c387863f0545d7591512e76ab0fc41",
        "sha256": "090l219mzc0gi33i3psgph6s2pwsc8qy4lyrqjdj4qzkvmaj65a7",
        "type": "tarball",
        "url": "https://github.com/nmattia/niv/archive/82e5cd1ad3c387863f0545d7591512e76ab0fc41.tar.gz",
        "url_template": "https://github.com/<owner>/<repo>/archive/<rev>.tar.gz"
    },
    "nixos-hardware": {
        "branch": "master",
        "description": "A collection of NixOS modules covering hardware quirks.",
        "homepage": "",
        "owner": "NixOS",
        "repo": "nixos-hardware",
        "rev": "39a7bfc496d2ddfce73fe9542af1f2029ba4fe39",
        "sha256": "02z72j7v4qn6skc6rv85m2jvnnd3rv0rflri7ypjv4k1ls34lk3d",
        "type": "tarball",
        "url": "https://github.com/NixOS/nixos-hardware/archive/39a7bfc496d2ddfce73fe9542af1f2029ba4fe39.tar.gz",
        "url_template": "https://github.com/<owner>/<repo>/archive/<rev>.tar.gz"
    },
    "nixpkgs": {
        "branch": "nixos-unstable",
        "description": "Nix Packages collection",
        "homepage": "",
        "owner": "NixOS",
        "repo": "nixpkgs",
        "rev": "83658b28fe638a170a19b8933aa008b30640fbd1",
        "sha256": "11knahk5j90aaxskh204dbg4px5mgrp7pbgm77g6ck2cbv8imyaj",
        "type": "tarball",
        "url": "https://github.com/NixOS/nixpkgs/archive/83658b28fe638a170a19b8933aa008b30640fbd1.tar.gz",
        "url_template": "https://github.com/<owner>/<repo>/archive/<rev>.tar.gz"
    }
}
